{
  "2025-10": {
    "2025-10-01": [
      "Leandro Lucero",
      "Hernan Dinter"
    ],
    "2025-10-02": [
      "Daniela Gonzalez",
      "Tobías Martinez"
    ],
    "2025-10-03": [
      "Matías Alvarez",
      "Analia Argüello"
    ],
    "2025-10-04": [
      "Leandro Lucero",
      "Hernan Dinter"
    ],
    "2025-10-06": [
      "Daniela Gonzalez",
      "Tobías Martinez"
    ],
    "2025-10-07": [
      "Matías Alvarez",
      "Analia Argüello"
    ],
    "2025-10-08": [
      "Leandro Lucero",
      "Hernan Dinter"
    ],
    "2025-10-09": [
      "Daniela Gonzalez",
      "Tobías Martinez"
    ],
    "2025-10-10": [
      "Matías Alvarez",
      "Analia Argüello"
    ],
    "2025-10-11": [
      "Leandro Lucero",
      "Hernan Dinter"
    ],
    "2025-10-13": [
      "Daniela Gonzalez",
      "Tobías Martinez"
    ],
    "2025-10-14": [
      "Matías Alvarez",
      "Analia Argüello"
    ],
    "2025-10-15": [
      "Leandro Lucero",
      "Hernan Dinter"
    ],
    "2025-10-16": [
      "Daniela Gonzalez",
      "Tobías Martinez"
    ],
    "2025-10-17": [
      "Matías Alvarez",
      "Analia Argüello"
    ],
    "2025-10-18": [
      "Leandro Lucero",
      "Hernan Dinter"
    ],
    "2025-10-20": [
      "Daniela Gonzalez",
      "Tobías Martinez"
    ],
    "2025-10-21": [
      "Matías Alvarez",
      "Analia Argüello"
    ],
    "2025-10-22": [
      "Leandro Lucero",
      "Hernan Dinter"
    ],
    "2025-10-23": [
      "Daniela Gonzalez",
      "Tobías Martinez"
    ],
    "2025-10-24": [
      "Matías Alvarez",
      "Analia Argüello"
    ],
    "2025-10-25": [
      "Leandro Lucero",
      "Hernan Dinter"
    ],
    "2025-10-27": [
      "Daniela Gonzalez",
      "Tobías Martinez"
    ],
    "2025-10-28": [
      "Matías Alvarez",
      "Analia Argüello"
    ],
    "2025-10-29": [
      "Leandro Lucero",
      "Hernan Dinter"
    ],
    "2025-10-30": [
      "Daniela Gonzalez",
      "Tobías Martinez"
    ],
    "2025-10-31": [
      "Matías Alvarez",
      "Analia Argüello"
    ]
  },
  "2025-11": {
    "2025-11-01": [
      "Leandro Lucero",
      "Hernan Dinter"
    ],
    "2025-11-03": [
      "Daniela Gonzalez",
      "Tobías Martinez"
    ],
    "2025-11-04": [
      "Matías Alvarez",
      "Analia Argüello"
    ],
    "2025-11-05": [
      "Leandro Lucero",
      "Daniela Gonzalez"
    ],
    "2025-11-06": [
      "Hernan Dinter",
      "Tobías Martinez"
    ],
    "2025-11-07": [
      "Matías Alvarez",
      "Analia Argüello"
    ],
    "2025-11-08": [
      "Daniela Gonzalez",
      "Matías Alvarez"
    ],
    "2025-11-10": [
      "Leandro Lucero",
      "Analia Argüello"
    ],
    "2025-11-11": [
      "Hernan Dinter",
      "Tobías Martinez"
    ],
    "2025-11-12": [
      "Hernan Dinter",
      "Matías Alvarez"
    ],
    "2025-11-13": [
      "Daniela Gonzalez",
      "Analia Argüello"
    ],
    "2025-11-14": [
      "Leandro Lucero",
      "Tobías Martinez"
    ],
    "2025-11-15": [
      "Tobías Martinez",
      "Analia Argüello"
    ],
    "2025-11-17": [
      "Hernan Dinter",
      "Matías Alvarez"
    ],
    "2025-11-18": [
      "Leandro Lucero",
      "Daniela Gonzalez"
    ],
    "2025-11-19": [
      "Tobías Martinez",
      "Analia Argüello"
    ],
    "2025-11-20": [
      "Leandro Lucero",
      "Matías Alvarez"
    ],
    "2025-11-21": [
      "Hernan Dinter",
      "Daniela Gonzalez"
    ],
    "2025-11-22": [
      "Hernan Dinter",
      "Analia Argüello"
    ],
    "2025-11-25": [
      "Tobías Martinez",
      "Matías Alvarez"
    ],
    "2025-11-26": [
      "Leandro Lucero",
      "Daniela Gonzalez"
    ],
    "2025-11-27": [
      "Leandro Lucero",
      "Hernan Dinter"
    ],
    "2025-11-28": [
      "Daniela Gonzalez",
      "Tobías Martinez"
    ],
    "2025-11-29": [
      "Matías Alvarez",
      "Analia Argüello"
    ]
  }
}