{
  "parejas": {
    "Hernan Dinter|Leandro Lucero": 6,
    "Daniela Gonzalez|Tobías Martinez": 4,
    "Analia Argüello|Matías Alvarez": 6,
    "Daniela Gonzalez|Leandro Lucero": 5,
    "Hernan Dinter|Tobías Martinez": 5,
    "Daniela Gonzalez|Matías Alvarez": 5,
    "Analia Argüello|Leandro Lucero": 4,
    "Hernan Dinter|Matías Alvarez": 4,
    "Analia Argüello|Daniela Gonzalez": 4,
    "Leandro Lucero|Tobías Martinez": 4,
    "Analia Argüello|Tobías Martinez": 7,
    "Leandro Lucero|Matías Alvarez": 5,
    "Daniela Gonzalez|Hernan Dinter": 6,
    "Analia Argüello|Hernan Dinter": 3,
    "Matías Alvarez|Tobías Martinez": 4
  },
  "diasPorAgente": {
    "Leandro Lucero": {
      "1": 3,
      "2": 3,
      "3": 5,
      "4": 4,
      "5": 4,
      "6": 5
    },
    "Hernan Dinter": {
      "1": 3,
      "2": 4,
      "3": 4,
      "4": 4,
      "5": 4,
      "6": 5
    },
    "Daniela Gonzalez": {
      "1": 3,
      "2": 4,
      "3": 4,
      "4": 4,
      "5": 4,
      "6": 5
    },
    "Tobías Martinez": {
      "1": 3,
      "2": 5,
      "3": 3,
      "4": 4,
      "5": 4,
      "6": 5
    },
    "Matías Alvarez": {
      "1": 3,
      "2": 4,
      "3": 4,
      "4": 4,
      "5": 4,
      "6": 5
    },
    "Analia Argüello": {
      "1": 3,
      "2": 4,
      "3": 4,
      "4": 4,
      "5": 4,
      "6": 5
    }
  }
}